sip_pbc/__init__.py
sip_pbc/release.py
sip_pbc/tasks.py
skasip_pbc-1.3.0.dist-info/LICENSE.md
skasip_pbc-1.3.0.dist-info/METADATA
skasip_pbc-1.3.0.dist-info/WHEEL
skasip_pbc-1.3.0.dist-info/top_level.txt
skasip_pbc-1.3.0.dist-info/RECORD
