Metadata-Version: 2.1
Name: skasip-pbc
Version: 1.3.0
Summary: SIP Processing Block Controller library.
Home-page: https://github.com/SKA-ScienceDataProcessor/integration-prototype/tree/master/sip/execution_control/processing_block_controller
Author: SKA SDP SIP team.
License: UNKNOWN
Platform: UNKNOWN
Classifier: Programming Language :: Python :: 3 :: Only
Classifier: Development Status :: 1 - Planning
Classifier: License :: OSI Approved :: BSD License
Requires-Dist: skasip-config-db (>=1.2.2)
Requires-Dist: skasip-docker-swarm (>=1.0.7)
Requires-Dist: skasip-logging (>=1.0.14)
Requires-Dist: redis (==2.10.6)
Requires-Dist: jinja2 (==2.10)
Requires-Dist: celery (==4.2.1)
Requires-Dist: PyYAML (==4.2b4)
